sphinxcontrib_githubcomments-0.5.0-py2.7-nspkg.pth
sphinxcontrib/githubcomments/__init__.py
sphinxcontrib/githubcomments/_version.py
sphinxcontrib/githubcomments/ext.py
sphinxcontrib/githubcomments/_static/githubcomments.css
sphinxcontrib/githubcomments/_static/githubcomments.js
sphinxcontrib/githubcomments/_static/cljs/core.js
sphinxcontrib/githubcomments/_static/cljs/pprint.js
sphinxcontrib/githubcomments/_static/clojure/string.js
sphinxcontrib/githubcomments/_static/goog/base.js
sphinxcontrib/githubcomments/_static/goog/array/array.js
sphinxcontrib/githubcomments/_static/goog/asserts/asserts.js
sphinxcontrib/githubcomments/_static/goog/debug/error.js
sphinxcontrib/githubcomments/_static/goog/dom/nodetype.js
sphinxcontrib/githubcomments/_static/goog/object/object.js
sphinxcontrib/githubcomments/_static/goog/string/string.js
sphinxcontrib/githubcomments/_static/goog/string/stringbuffer.js
sphinxcontrib_githubcomments-0.5.0.dist-info/DESCRIPTION.rst
sphinxcontrib_githubcomments-0.5.0.dist-info/METADATA
sphinxcontrib_githubcomments-0.5.0.dist-info/RECORD
sphinxcontrib_githubcomments-0.5.0.dist-info/WHEEL
sphinxcontrib_githubcomments-0.5.0.dist-info/metadata.json
sphinxcontrib_githubcomments-0.5.0.dist-info/namespace_packages.txt
sphinxcontrib_githubcomments-0.5.0.dist-info/top_level.txt
