Metadata-Version: 2.0
Name: sphinxcontrib-githubcomments
Version: 0.5.0
Summary: Add GitHub comments to your Sphinx docs.
Home-page: https://github.com/Julian/sphinxcontrib-githubcomments
Author: Julian Berman
Author-email: Julian@GrayVines.com
License: MIT
Platform: UNKNOWN
Classifier: Development Status :: 3 - Alpha
Classifier: License :: OSI Approved :: MIT License
Classifier: Operating System :: OS Independent
Classifier: Programming Language :: Python
Classifier: Programming Language :: Python :: 2.7
Classifier: Programming Language :: Python :: 2
Classifier: Programming Language :: Python :: Implementation :: CPython
Classifier: Programming Language :: Python :: Implementation :: PyPy
